fmcapi/__init__.py
fmcapi/fmc.py
fmcapi/api_objects/__init__.py
fmcapi/api_objects/apiclasstemplate.py
fmcapi/api_objects/helper_functions.py
fmcapi/api_objects/audit_services/__init__.py
fmcapi/api_objects/audit_services/audit_records.py
fmcapi/api_objects/deployment_services/__init__.py
fmcapi/api_objects/deployment_services/deployabledevices.py
fmcapi/api_objects/deployment_services/deploymentrequests.py
fmcapi/api_objects/device_clusters/__init__.py
fmcapi/api_objects/device_clusters/ftddevicecluster.py
fmcapi/api_objects/device_group_services/__init__.py
fmcapi/api_objects/device_group_services/devicegrouprecords.py
fmcapi/api_objects/device_ha_pair_services/__init__.py
fmcapi/api_objects/device_ha_pair_services/failoverinterfacemacaddressconfigs.py
fmcapi/api_objects/device_ha_pair_services/ftddevicehapairs.py
fmcapi/api_objects/device_ha_pair_services/monitoredinterfaces.py
fmcapi/api_objects/device_services/__init__.py
fmcapi/api_objects/device_services/bridgegroupinterfaces.py
fmcapi/api_objects/device_services/copyconfigrequests.py
fmcapi/api_objects/device_services/devicerecords.py
fmcapi/api_objects/device_services/etherchannelinterfaces.py
fmcapi/api_objects/device_services/fpinterfacestatistics.py
fmcapi/api_objects/device_services/fplogicalinterfaces.py
fmcapi/api_objects/device_services/fpphysicalinterfaces.py
fmcapi/api_objects/device_services/inlinesets.py
fmcapi/api_objects/device_services/interfaceevents.py
fmcapi/api_objects/device_services/ipv4staticroutes.py
fmcapi/api_objects/device_services/ipv6staticroutes.py
fmcapi/api_objects/device_services/physicalinterfaces.py
fmcapi/api_objects/device_services/redundantinterfaces.py
fmcapi/api_objects/device_services/staticroutes.py
fmcapi/api_objects/device_services/subinterfaces.py
fmcapi/api_objects/device_services/virtualswitches.py
fmcapi/api_objects/device_services/vlaninterfaces.py
fmcapi/api_objects/integration_services/__init__.py
fmcapi/api_objects/integration_services/cloudeventsconfigs.py
fmcapi-20230519.0.dist-info/LICENSE.md
fmcapi-20230519.0.dist-info/METADATA
fmcapi-20230519.0.dist-info/WHEEL
fmcapi-20230519.0.dist-info/top_level.txt
fmcapi-20230519.0.dist-info/RECORD
