Metadata-Version: 2.1
Name: fmcapi
Version: 20230519.0
Summary: Easier interface to Cisco's FMC API than writing your own way.
Home-page: https://github.com/daxm/fmcapi
Author: Dax Mickelson
Author-email: dmickels@cisco.com
License: BSD
Keywords: fmcapi fmc ftd security cisco ngfw api firepower
Platform: UNKNOWN
Classifier: Development Status :: 5 - Production/Stable
Classifier: Environment :: Plugins
Classifier: Intended Audience :: System Administrators
Classifier: Intended Audience :: Developers
Classifier: Intended Audience :: Other Audience
Classifier: License :: OSI Approved :: BSD License
Classifier: Natural Language :: English
Classifier: Operating System :: POSIX :: Linux
Classifier: Operating System :: MacOS
Classifier: Operating System :: Microsoft
Classifier: Programming Language :: Python :: 3
Classifier: Topic :: Security
Classifier: Topic :: Software Development
Classifier: Topic :: Software Development :: Libraries :: Python Modules
Classifier: Topic :: System :: Networking :: Firewalls
Classifier: Topic :: System :: Systems Administration
Classifier: Topic :: Utilities
Requires-Python: >=3.6
Requires-Dist: requests
Requires-Dist: datetime
Requires-Dist: ipaddress
